{
  "scene_name": "ganon",
  "scene_num": 10,
  "is_mq": false,
  "scene_header_file": "/scene/ganon_info.zsi",
  "room_count": 10,
  "spawn_points": [
    {
      "id": 12928,
      "pos": [
        1,
        0,
        0
      ],
      "rot": [
        1792,
        1537,
        2050
      ],
      "params": 0
    },
    {
      "id": 0,
      "pos": [
        210,
        -220,
        974
      ],
      "rot": [
        0,
        -32767,
        0
      ],
      "params": 4095
    },
    {
      "id": 0,
      "pos": [
        -2,
        1520,
        579
      ],
      "rot": [
        0,
        0,
        0
      ],
      "params": 3583
    }
  ],
  "transition_actors": [
    {
      "front_room": 12,
      "front_face": 3,
      "back_room": 29,
      "back_face": 1,
      "id": 0,
      "pos": [
        0,
        0,
        3583
      ],
      "rot_y": 1332,
      "params": 1055
    },
    {
      "front_room": 0,
      "front_face": 0,
      "back_room": 122,
      "back_face": 69,
      "id": 0,
      "pos": [
        17786,
        4880,
        12593
      ],
      "rot_y": 18481,
      "params": 18504
    },
    {
      "front_room": 200,
      "front_face": 200,
      "back_room": 130,
      "back_face": 184,
      "id": -18248,
      "pos": [
        20303,
        4943,
        19
      ],
      "rot_y": 0,
      "params": 17786
    },
    {
      "front_room": 0,
      "front_face": 0,
      "back_room": 122,
      "back_face": 68,
      "id": 1224,
      "pos": [
        27756,
        -8084,
        -8065
      ],
      "rot_y": -6426,
      "params": 8345
    },
    {
      "front_room": 129,
      "front_face": 32,
      "back_room": 77,
      "back_face": 26,
      "id": 4611,
      "pos": [
        13,
        0,
        17992
      ],
      "rot_y": 0,
      "params": 17992
    },
    {
      "front_room": 232,
      "front_face": 7,
      "back_room": 37,
      "back_face": 109,
      "id": 19869,
      "pos": [
        -26035,
        -22874,
        -3187
      ],
      "rot_y": 1921,
      "params": 10112
    },
    {
      "front_room": 255,
      "front_face": 0,
      "back_room": 18,
      "back_face": 51,
      "id": 0,
      "pos": [
        17992,
        0,
        17992
      ],
      "rot_y": 12980,
      "params": 0
    },
    {
      "front_room": 0,
      "front_face": 77,
      "back_room": 77,
      "back_face": 217,
      "id": 30673,
      "pos": [
        -3318,
        1921,
        0
      ],
      "rot_y": -12032,
      "params": 10380
    },
    {
      "front_room": 0,
      "front_face": 0,
      "back_room": 72,
      "back_face": 70,
      "id": 0,
      "pos": [
        17992,
        2024,
        26191
      ],
      "rot_y": -9933,
      "params": 63053
    },
    {
      "front_room": 234,
      "front_face": 217,
      "back_room": 102,
      "back_face": 72,
      "id": -8063,
      "pos": [
        20096,
        66,
        12
      ],
      "rot_y": 0,
      "params": 17992
    },
    {
      "front_room": 0,
      "front_face": 0,
      "back_room": 72,
      "back_face": 70,
      "id": 2024,
      "pos": [
        23220,
        -19673,
        10061
      ],
      "rot_y": -12801,
      "params": 3387
    }
  ],
  "rooms": [
    {
      "room_num": 0,
      "file": "/scene/ganon_0_info.zsi",
      "actors": [
        {
          "id": 2,
          "pos": [
            0,
            313,
            164
          ],
          "rot": [
            133,
            13,
            27
          ],
          "params": 0,
          "room": 0
        },
        {
          "id": 59,
          "pos": [
            -13,
            0,
            29
          ],
          "rot": [
            0,
            0,
            0
          ],
          "params": 255,
          "room": 0
        },
        {
          "id": 37,
          "pos": [
            26,
            0,
            -133
          ],
          "rot": [
            0,
            -16384,
            0
          ],
          "params": 65534,
          "room": 0
        },
        {
          "id": 37,
          "pos": [
            35,
            0,
            119
          ],
          "rot": [
            0,
            -16384,
            0
          ],
          "params": 65534,
          "room": 0
        },
        {
          "id": 8,
          "pos": [
            232,
            120,
            237
          ],
          "rot": [
            0,
            0,
            0
          ],
          "params": 1012,
          "room": 0
        },
        {
          "id": 8,
          "pos": [
            240,
            120,
            -236
          ],
          "rot": [
            0,
            0,
            0
          ],
          "params": 1012,
          "room": 0
        },
        {
          "id": 8,
          "pos": [
            -236,
            120,
            -237
          ],
          "rot": [
            0,
            0,
            0
          ],
          "params": 1012,
          "room": 0
        }
      ],
      "objects": [
        1,
        258,
        0,
        64,
        0
      ]
    },
    {
      "room_num": 1,
      "file": "/scene/ganon_1_info.zsi",
      "actors": [
        {
          "id": 2,
          "pos": [
            0,
            313,
            164
          ],
          "rot": [
            133,
            13,
            27
          ],
          "params": 0,
          "room": 1
        },
        {
          "id": 59,
          "pos": [
            534,
            120,
            -217
          ],
          "rot": [
            0,
            0,
            0
          ],
          "params": 255,
          "room": 1
        },
        {
          "id": 8,
          "pos": [
            645,
            180,
            -346
          ],
          "rot": [
            0,
            0,
            0
          ],
          "params": 1012,
          "room": 1
        },
        {
          "id": 8,
          "pos": [
            450,
            240,
            -538
          ],
          "rot": [
            0,
            0,
            0
          ],
          "params": 1012,
          "room": 1
        },
        {
          "id": 8,
          "pos": [
            491,
            180,
            -254
          ],
          "rot": [
            0,
            0,
            0
          ],
          "params": 1012,
          "room": 1
        },
        {
          "id": 8,
          "pos": [
            362,
            240,
            -382
          ],
          "rot": [
            0,
            0,
            0
          ],
          "params": 1012,
          "room": 1
        }
      ],
      "objects": [
        1,
        258,
        0,
        64,
        0
      ]
    },
    {
      "room_num": 2,
      "file": "/scene/ganon_2_info.zsi",
      "actors": [
        {
          "id": 313,
          "pos": [
            164,
            133,
            13
          ],
          "rot": [
            27,
            50,
            14
          ],
          "params": 22351,
          "room": 2
        },
        {
          "id": 59,
          "pos": [
            174,
            260,
            29
          ],
          "rot": [
            0,
            0,
            0
          ],
          "params": 254,
          "room": 2
        },
        {
          "id": 8,
          "pos": [
            234,
            374,
            237
          ],
          "rot": [
            0,
            0,
            0
          ],
          "params": 1012,
          "room": 2
        },
        {
          "id": 8,
          "pos": [
            240,
            374,
            -238
          ],
          "rot": [
            0,
            0,
            0
          ],
          "params": 1012,
          "room": 2
        },
        {
          "id": 8,
          "pos": [
            -237,
            374,
            -238
          ],
          "rot": [
            0,
            0,
            0
          ],
          "params": 1012,
          "room": 2
        },
        {
          "id": 8,
          "pos": [
            -235,
            374,
            239
          ],
          "rot": [
            0,
            0,
            0
          ],
          "params": 1012,
          "room": 2
        },
        {
          "id": 2,
          "pos": [
            -183,
            260,
            -12
          ],
          "rot": [
            0,
            -32767,
            0
          ],
          "params": 65535,
          "room": 2
        },
        {
          "id": 2,
          "pos": [
            161,
            260,
            -7
          ],
          "rot": [
            0,
            -32767,
            0
          ],
          "params": 65535,
          "room": 2
        },
        {
          "id": 73,
          "pos": [
            2,
            260,
            -1
          ],
          "rot": [
            0,
            0,
            0
          ],
          "params": 28618,
          "room": 2
        },
        {
          "id": 391,
          "pos": [
            -94,
            260,
            -11
          ],
          "rot": [
            0,
            0,
            0
          ],
          "params": 11263,
          "room": 2
        }
      ],
      "objects": [
        2049,
        258,
        0,
        64,
        0,
        4432,
        3
      ]
    },
    {
      "room_num": 3,
      "file": "/scene/ganon_3_info.zsi",
      "actors": [
        {
          "id": 313,
          "pos": [
            164,
            133,
            13
          ],
          "rot": [
            27,
            50,
            14
          ],
          "params": 0,
          "room": 3
        },
        {
          "id": 59,
          "pos": [
            37,
            300,
            622
          ],
          "rot": [
            0,
            0,
            0
          ],
          "params": 253,
          "room": 3
        },
        {
          "id": 8,
          "pos": [
            345,
            440,
            644
          ],
          "rot": [
            0,
            0,
            0
          ],
          "params": 1012,
          "room": 3
        },
        {
          "id": 8,
          "pos": [
            255,
            440,
            490
          ],
          "rot": [
            0,
            0,
            0
          ],
          "params": 1012,
          "room": 3
        },
        {
          "id": 8,
          "pos": [
            537,
            500,
            451
          ],
          "rot": [
            0,
            0,
            0
          ],
          "params": 1012,
          "room": 3
        },
        {
          "id": 8,
          "pos": [
            385,
            500,
            361
          ],
          "rot": [
            0,
            0,
            0
          ],
          "params": 1012,
          "room": 3
        }
      ],
      "objects": [
        1,
        258,
        0,
        64,
        0,
        60752,
        1
      ]
    },
    {
      "room_num": 4,
      "file": "/scene/ganon_4_info.zsi",
      "actors": [
        {
          "id": 3,
          "pos": [
            0,
            313,
            164
          ],
          "rot": [
            133,
            13,
            262
          ],
          "params": 14,
          "room": 4
        },
        {
          "id": 59,
          "pos": [
            37,
            520,
            -122
          ],
          "rot": [
            0,
            0,
            0
          ],
          "params": 252,
          "room": 4
        },
        {
          "id": 275,
          "pos": [
            -291,
            520,
            37
          ],
          "rot": [
            0,
            16384,
            0
          ],
          "params": 65282,
          "room": 4
        },
        {
          "id": 275,
          "pos": [
            -290,
            520,
            -32
          ],
          "rot": [
            0,
            16384,
            0
          ],
          "params": 65283,
          "room": 4
        },
        {
          "id": 8,
          "pos": [
            234,
            630,
            238
          ],
          "rot": [
            0,
            0,
            0
          ],
          "params": 1012,
          "room": 4
        },
        {
          "id": 8,
          "pos": [
            241,
            630,
            -236
          ],
          "rot": [
            0,
            0,
            0
          ],
          "params": 1012,
          "room": 4
        },
        {
          "id": 8,
          "pos": [
            -236,
            630,
            -236
          ],
          "rot": [
            0,
            0,
            0
          ],
          "params": 1012,
          "room": 4
        }
      ],
      "objects": [
        1,
        258,
        0,
        64,
        0,
        9680
      ]
    },
    {
      "room_num": 5,
      "file": "/scene/ganon_5_info.zsi",
      "actors": [
        {
          "id": 0,
          "pos": [
            64,
            0,
            5200
          ],
          "rot": [
            3,
            0,
            313
          ],
          "params": 176,
          "room": 5
        },
        {
          "id": 59,
          "pos": [
            -650,
            560,
            16
          ],
          "rot": [
            0,
            0,
            0
          ],
          "params": 251,
          "room": 5
        },
        {
          "id": 8,
          "pos": [
            -644,
            720,
            446
          ],
          "rot": [
            0,
            0,
            0
          ],
          "params": 1012,
          "room": 5
        },
        {
          "id": 8,
          "pos": [
            -490,
            720,
            355
          ],
          "rot": [
            0,
            0,
            0
          ],
          "params": 1012,
          "room": 5
        },
        {
          "id": 8,
          "pos": [
            -363,
            780,
            484
          ],
          "rot": [
            0,
            0,
            0
          ],
          "params": 1012,
          "room": 5
        }
      ],
      "objects": [
        1,
        258
      ]
    },
    {
      "room_num": 6,
      "file": "/scene/ganon_6_info.zsi",
      "actors": [
        {
          "id": 0,
          "pos": [
            64,
            0,
            -8240
          ],
          "rot": [
            7,
            14400,
            313
          ],
          "params": 176,
          "room": 6
        }
      ],
      "objects": [
        513,
        258
      ]
    },
    {
      "room_num": 7,
      "file": "/scene/ganon_7_info.zsi",
      "actors": [
        {
          "id": 3,
          "pos": [
            0,
            313,
            164
          ],
          "rot": [
            133,
            13,
            27
          ],
          "params": 176,
          "room": 7
        },
        {
          "id": 59,
          "pos": [
            323,
            -220,
            639
          ],
          "rot": [
            0,
            0,
            0
          ],
          "params": 255,
          "room": 7
        },
        {
          "id": 19,
          "pos": [
            83,
            140,
            572
          ],
          "rot": [
            0,
            0,
            0
          ],
          "params": 0,
          "room": 7
        },
        {
          "id": 19,
          "pos": [
            225,
            140,
            650
          ],
          "rot": [
            0,
            0,
            0
          ],
          "params": 0,
          "room": 7
        },
        {
          "id": 19,
          "pos": [
            365,
            140,
            575
          ],
          "rot": [
            0,
            0,
            0
          ],
          "params": 0,
          "room": 7
        },
        {
          "id": 19,
          "pos": [
            -352,
            27,
            477
          ],
          "rot": [
            0,
            0,
            0
          ],
          "params": 0,
          "room": 7
        },
        {
          "id": 19,
          "pos": [
            -519,
            160,
            7
          ],
          "rot": [
            0,
            0,
            0
          ],
          "params": 0,
          "room": 7
        },
        {
          "id": 19,
          "pos": [
            -532,
            78,
            360
          ],
          "rot": [
            0,
            0,
            0
          ],
          "params": 0,
          "room": 7
        },
        {
          "id": 19,
          "pos": [
            -173,
            -37,
            657
          ],
          "rot": [
            0,
            0,
            0
          ],
          "params": 0,
          "room": 7
        },
        {
          "id": 94,
          "pos": [
            141,
            -220,
            460
          ],
          "rot": [
            0,
            0,
            0
          ],
          "params": 9216,
          "room": 7
        },
        {
          "id": 94,
          "pos": [
            294,
            -220,
            461
          ],
          "rot": [
            0,
            0,
            0
          ],
          "params": 9216,
          "room": 7
        },
        {
          "id": 94,
          "pos": [
            -587,
            0,
            -68
          ],
          "rot": [
            0,
            0,
            0
          ],
          "params": 9216,
          "room": 7
        }
      ],
      "objects": [
        1,
        258,
        0,
        64,
        0,
        13776
      ]
    },
    {
      "room_num": 8,
      "file": "/scene/ganon_8_info.zsi",
      "actors": [
        {
          "id": 0,
          "pos": [
            64,
            0,
            -21808
          ],
          "rot": [
            5,
            15934,
            313
          ],
          "params": 176,
          "room": 8
        },
        {
          "id": 59,
          "pos": [
            -7,
            780,
            197
          ],
          "rot": [
            0,
            0,
            0
          ],
          "params": 250,
          "room": 8
        },
        {
          "id": 273,
          "pos": [
            -422,
            800,
            -258
          ],
          "rot": [
            0,
            0,
            0
          ],
          "params": 16398,
          "room": 8
        },
        {
          "id": 273,
          "pos": [
            -382,
            800,
            -300
          ],
          "rot": [
            0,
            0,
            0
          ],
          "params": 16899,
          "room": 8
        },
        {
          "id": 273,
          "pos": [
            -342,
            800,
            -341
          ],
          "rot": [
            0,
            0,
            0
          ],
          "params": 17423,
          "room": 8
        },
        {
          "id": 273,
          "pos": [
            -298,
            800,
            -383
          ],
          "rot": [
            0,
            0,
            0
          ],
          "params": 17935,
          "room": 8
        },
        {
          "id": 273,
          "pos": [
            -257,
            800,
            -424
          ],
          "rot": [
            0,
            0,
            0
          ],
          "params": 18435,
          "room": 8
        },
        {
          "id": 273,
          "pos": [
            -382,
            800,
            -259
          ],
          "rot": [
            0,
            0,
            0
          ],
          "params": 18953,
          "room": 8
        },
        {
          "id": 273,
          "pos": [
            -342,
            800,
            -300
          ],
          "rot": [
            0,
            0,
            0
          ],
          "params": 19465,
          "room": 8
        },
        {
          "id": 273,
          "pos": [
            -301,
            800,
            -341
          ],
          "rot": [
            0,
            0,
            0
          ],
          "params": 19971,
          "room": 8
        },
        {
          "id": 273,
          "pos": [
            -258,
            800,
            -383
          ],
          "rot": [
            0,
            0,
            0
          ],
          "params": 20543,
          "room": 8
        },
        {
          "id": 273,
          "pos": [
            418,
            800,
            -261
          ],
          "rot": [
            0,
            0,
            0
          ],
          "params": 21055,
          "room": 8
        },
        {
          "id": 273,
          "pos": [
            377,
            800,
            -301
          ],
          "rot": [
            0,
            0,
            0
          ],
          "params": 21513,
          "room": 8
        },
        {
          "id": 273,
          "pos": [
            338,
            800,
            -340
          ],
          "rot": [
            0,
            0,
            0
          ],
          "params": 22025,
          "room": 8
        },
        {
          "id": 273,
          "pos": [
            300,
            800,
            -380
          ],
          "rot": [
            0,
            0,
            0
          ],
          "params": 22531,
          "room": 8
        },
        {
          "id": 273,
          "pos": [
            260,
            800,
            -420
          ],
          "rot": [
            0,
            0,
            0
          ],
          "params": 23043,
          "room": 8
        },
        {
          "id": 273,
          "pos": [
            378,
            800,
            -261
          ],
          "rot": [
            0,
            0,
            0
          ],
          "params": 23555,
          "room": 8
        },
        {
          "id": 273,
          "pos": [
            337,
            800,
            -300
          ],
          "rot": [
            0,
            0,
            0
          ],
          "params": 24127,
          "room": 8
        },
        {
          "id": 273,
          "pos": [
            299,
            800,
            -340
          ],
          "rot": [
            0,
            0,
            0
          ],
          "params": 24639,
          "room": 8
        }
      ],
      "objects": [
        16385,
        258
      ]
    },
    {
      "room_num": 9,
      "file": "/scene/ganon_9_info.zsi",
      "actors": [],
      "objects": [
        1,
        258
      ]
    }
  ],
  "actor_id_set": [
    0,
    2,
    3,
    8,
    19,
    37,
    59,
    73,
    94,
    273,
    275,
    313,
    391
  ],
  "total_actor_spawns": 73
}