{
  "scene_name": "spot16",
  "scene_num": 96,
  "is_mq": false,
  "scene_header_file": "/scene/spot16_info.zsi",
  "room_count": 1,
  "spawn_points": [
    {
      "id": 2,
      "pos": [
        0,
        -30224,
        0
      ],
      "rot": [
        9,
        0,
        -30212
      ],
      "params": 0
    },
    {
      "id": 0,
      "pos": [
        -1344,
        118,
        2221
      ],
      "rot": [
        0,
        -21844,
        0
      ],
      "params": 4095
    },
    {
      "id": 0,
      "pos": [
        -407,
        1191,
        -1860
      ],
      "rot": [
        0,
        0,
        0
      ],
      "params": 4095
    },
    {
      "id": 0,
      "pos": [
        230,
        3263,
        -4670
      ],
      "rot": [
        0,
        -3641,
        0
      ],
      "params": 4095
    },
    {
      "id": 0,
      "pos": [
        -1671,
        677,
        -924
      ],
      "rot": [
        0,
        0,
        0
      ],
      "params": 4095
    },
    {
      "id": 0,
      "pos": [
        -249,
        3314,
        -4497
      ],
      "rot": [
        0,
        5097,
        0
      ],
      "params": 4095
    }
  ],
  "transition_actors": [
    {
      "front_room": 0,
      "front_face": 0,
      "back_room": 255,
      "back_face": 13,
      "id": 401,
      "pos": [
        333,
        327,
        4
      ],
      "rot_y": 789,
      "params": 0
    },
    {
      "front_room": 0,
      "front_face": 0,
      "back_room": 250,
      "back_face": 70,
      "id": 16384,
      "pos": [
        18204,
        1224,
        26728
      ],
      "rot_y": 61,
      "params": 0
    },
    {
      "front_room": 255,
      "front_face": 255,
      "back_room": 119,
      "back_face": 0,
      "id": 0,
      "pos": [
        13129,
        -20675,
        15746
      ],
      "rot_y": 0,
      "params": 18170
    },
    {
      "front_room": 0,
      "front_face": 32,
      "back_room": 75,
      "back_face": 71,
      "id": 1824,
      "pos": [
        -32126,
        109,
        0
      ],
      "rot_y": -1,
      "params": 255
    },
    {
      "front_room": 0,
      "front_face": 0,
      "back_room": 109,
      "back_face": 109,
      "id": -32157,
      "pos": [
        -20571,
        0,
        18170
      ],
      "rot_y": 16384,
      "params": 18204
    },
    {
      "front_room": 200,
      "front_face": 4,
      "back_room": 130,
      "back_face": 68,
      "id": 25,
      "pos": [
        0,
        -21761,
        51
      ],
      "rot_y": 0,
      "params": 5171
    },
    {
      "front_room": 89,
      "front_face": 119,
      "back_room": 61,
      "back_face": 61,
      "id": 0,
      "pos": [
        18170,
        0,
        18170
      ],
      "rot_y": 1064,
      "params": 17448
    },
    {
      "front_room": 135,
      "front_face": 0,
      "back_room": 0,
      "back_face": 0,
      "id": 13107,
      "pos": [
        114,
        0,
        -19091
      ],
      "rot_y": 255,
      "params": 7680
    },
    {
      "front_room": 0,
      "front_face": 0,
      "back_room": 250,
      "back_face": 70,
      "id": 0,
      "pos": [
        17992,
        -242,
        0
      ],
      "rot_y": 0,
      "params": 0
    },
    {
      "front_room": 0,
      "front_face": 0,
      "back_room": 0,
      "back_face": 0,
      "id": 0,
      "pos": [
        0,
        0,
        0
      ],
      "rot_y": 0,
      "params": 18170
    },
    {
      "front_room": 0,
      "front_face": 0,
      "back_room": 72,
      "back_face": 70,
      "id": -242,
      "pos": [
        0,
        0,
        0
      ],
      "rot_y": 0,
      "params": 0
    },
    {
      "front_room": 0,
      "front_face": 0,
      "back_room": 0,
      "back_face": 0,
      "id": 0,
      "pos": [
        0,
        0,
        18170
      ],
      "rot_y": 0,
      "params": 17992
    }
  ],
  "rooms": [
    {
      "room_num": 0,
      "file": "/scene/spot16_0_info.zsi",
      "actors": [
        {
          "id": 146,
          "pos": [
            286,
            303,
            305
          ],
          "rot": [
            355,
            392,
            36
          ],
          "params": 14,
          "room": 0
        },
        {
          "id": 59,
          "pos": [
            -688,
            1943,
            -285
          ],
          "rot": [
            0,
            0,
            0
          ],
          "params": 21,
          "room": 0
        },
        {
          "id": 21,
          "pos": [
            -625,
            1793,
            -55
          ],
          "rot": [
            0,
            0,
            0
          ],
          "params": 2562,
          "room": 0
        },
        {
          "id": 21,
          "pos": [
            -1060,
            1693,
            -51
          ],
          "rot": [
            0,
            0,
            0
          ],
          "params": 1793,
          "room": 0
        },
        {
          "id": 333,
          "pos": [
            -42,
            3347,
            -4408
          ],
          "rot": [
            0,
            2731,
            0
          ],
          "params": 531,
          "room": 0
        },
        {
          "id": 441,
          "pos": [
            40,
            2872,
            -3935
          ],
          "rot": [
            0,
            0,
            0
          ],
          "params": 14340,
          "room": 0
        },
        {
          "id": 430,
          "pos": [
            -1235,
            1159,
            891
          ],
          "rot": [
            0,
            0,
            0
          ],
          "params": 65516,
          "room": 0
        },
        {
          "id": 149,
          "pos": [
            62,
            2618,
            -3982
          ],
          "rot": [
            16384,
            0,
            0
          ],
          "params": 0,
          "room": 0
        },
        {
          "id": 149,
          "pos": [
            -157,
            2783,
            -3982
          ],
          "rot": [
            16384,
            0,
            0
          ],
          "params": 0,
          "room": 0
        },
        {
          "id": 149,
          "pos": [
            15,
            3040,
            -3981
          ],
          "rot": [
            16384,
            0,
            0
          ],
          "params": 0,
          "room": 0
        },
        {
          "id": 27,
          "pos": [
            -2011,
            258,
            1953
          ],
          "rot": [
            0,
            6007,
            0
          ],
          "params": 65535,
          "room": 0
        },
        {
          "id": 27,
          "pos": [
            -1996,
            414,
            683
          ],
          "rot": [
            0,
            2912,
            0
          ],
          "params": 65535,
          "room": 0
        },
        {
          "id": 27,
          "pos": [
            -1918,
            357,
            1085
          ],
          "rot": [
            0,
            -3277,
            0
          ],
          "params": 65535,
          "room": 0
        },
        {
          "id": 27,
          "pos": [
            -1776,
            790,
            -19
          ],
          "rot": [
            0,
            -9101,
            0
          ],
          "params": 65535,
          "room": 0
        },
        {
          "id": 21,
          "pos": [
            -1500,
            1031,
            -1100
          ],
          "rot": [
            0,
            0,
            0
          ],
          "params": 7686,
          "room": 0
        },
        {
          "id": 208,
          "pos": [
            -1825,
            340,
            1189
          ],
          "rot": [
            0,
            -16384,
            0
          ],
          "params": 32769,
          "room": 0
        },
        {
          "id": 208,
          "pos": [
            -540,
            1448,
            -81
          ],
          "rot": [
            0,
            12743,
            0
          ],
          "params": 32770,
          "room": 0
        },
        {
          "id": 208,
          "pos": [
            -245,
            3305,
            -4480
          ],
          "rot": [
            0,
            4733,
            0
          ],
          "params": 32771,
          "room": 0
        },
        {
          "id": 155,
          "pos": [
            -688,
            1944,
            -285
          ],
          "rot": [
            0,
            -32767,
            13
          ],
          "params": 248,
          "room": 0
        },
        {
          "id": 155,
          "pos": [
            -383,
            1386,
            -1206
          ],
          "rot": [
            0,
            -32767,
            0
          ],
          "params": 343,
          "room": 0
        },
        {
          "id": 57,
          "pos": [
            -1300,
            120,
            2155
          ],
          "rot": [
            0,
            -10011,
            0
          ],
          "params": 1290,
          "room": 0
        },
        {
          "id": 57,
          "pos": [
            -735,
            1241,
            595
          ],
          "rot": [
            0,
            6554,
            0
          ],
          "params": 8458,
          "room": 0
        },
        {
          "id": 57,
          "pos": [
            -40,
            3298,
            -4410
          ],
          "rot": [
            0,
            4914,
            0
          ],
          "params": 8970,
          "room": 0
        },
        {
          "id": 57,
          "pos": [
            -1126,
            1661,
            44
          ],
          "rot": [
            0,
            8555,
            0
          ],
          "params": 11530,
          "room": 0
        },
        {
          "id": 38,
          "pos": [
            -746,
            1273,
            515
          ],
          "rot": [
            0,
            -5460,
            0
          ],
          "params": 65535,
          "room": 0
        },
        {
          "id": 149,
          "pos": [
            -1653,
            478,
            1194
          ],
          "rot": [
            16384,
            -16384,
            0
          ],
          "params": 36868,
          "room": 0
        },
        {
          "id": 463,
          "pos": [
            -1610,
            678,
            -735
          ],
          "rot": [
            0,
            0,
            0
          ],
          "params": 20482,
          "room": 0
        },
        {
          "id": 430,
          "pos": [
            -1300,
            1415,
            -560
          ],
          "rot": [
            0,
            20388,
            0
          ],
          "params": 5124,
          "room": 0
        },
        {
          "id": 334,
          "pos": [
            -1816,
            681,
            -513
          ],
          "rot": [
            0,
            0,
            0
          ],
          "params": 2816,
          "room": 0
        },
        {
          "id": 334,
          "pos": [
            -1831,
            681,
            -614
          ],
          "rot": [
            0,
            0,
            0
          ],
          "params": 2816,
          "room": 0
        },
        {
          "id": 334,
          "pos": [
            -1856,
            681,
            -536
          ],
          "rot": [
            0,
            0,
            0
          ],
          "params": 2816,
          "room": 0
        },
        {
          "id": 334,
          "pos": [
            -1878,
            681,
            -465
          ],
          "rot": [
            0,
            0,
            0
          ],
          "params": 2816,
          "room": 0
        },
        {
          "id": 334,
          "pos": [
            -1786,
            681,
            -550
          ],
          "rot": [
            0,
            0,
            0
          ],
          "params": 2816,
          "room": 0
        },
        {
          "id": 334,
          "pos": [
            -327,
            3280,
            -4286
          ],
          "rot": [
            0,
            0,
            0
          ],
          "params": 528,
          "room": 0
        },
        {
          "id": 337,
          "pos": [
            -383,
            1386,
            -1206
          ],
          "rot": [
            0,
            0,
            0
          ],
          "params": 2818,
          "room": 0
        },
        {
          "id": 321,
          "pos": [
            -1260,
            1408,
            540
          ],
          "rot": [
            0,
            0,
            0
          ],
          "params": 777,
          "room": 0
        },
        {
          "id": 321,
          "pos": [
            -1833,
            681,
            -571
          ],
          "rot": [
            0,
            0,
            0
          ],
          "params": 778,
          "room": 0
        },
        {
          "id": 321,
          "pos": [
            -299,
            1209,
            -1786
          ],
          "rot": [
            0,
            0,
            0
          ],
          "params": 779,
          "room": 0
        },
        {
          "id": 321,
          "pos": [
            -1300,
            1413,
            -496
          ],
          "rot": [
            0,
            15109,
            0
          ],
          "params": 802,
          "room": 0
        },
        {
          "id": 387,
          "pos": [
            -730,
            1346,
            464
          ],
          "rot": [
            0,
            0,
            0
          ],
          "params": 65344,
          "room": 0
        },
        {
          "id": 180,
          "pos": [
            -199,
            2031,
            -3060
          ],
          "rot": [
            0,
            0,
            0
          ],
          "params": 5,
          "room": 0
        },
        {
          "id": 430,
          "pos": [
            -311,
            1500,
            -393
          ],
          "rot": [
            0,
            -4914,
            0
          ],
          "params": 64549,
          "room": 0
        },
        {
          "id": 229,
          "pos": [
            102,
            5582,
            -6517
          ],
          "rot": [
            0,
            0,
            0
          ],
          "params": 65535,
          "room": 0
        },
        {
          "id": 205,
          "pos": [
            -1678,
            684,
            -690
          ],
          "rot": [
            0,
            0,
            0
          ],
          "params": 1279,
          "room": 0
        },
        {
          "id": 294,
          "pos": [
            -1610,
            678,
            -735
          ],
          "rot": [
            0,
            0,
            0
          ],
          "params": 7942,
          "room": 0
        },
        {
          "id": 389,
          "pos": [
            -237,
            3370,
            -4462
          ],
          "rot": [
            0,
            4733,
            41
          ],
          "params": 36547,
          "room": 0
        },
        {
          "id": 430,
          "pos": [
            -1601,
            701,
            -475
          ],
          "rot": [
            0,
            0,
            0
          ],
          "params": 65510,
          "room": 0
        },
        {
          "id": 76,
          "pos": [
            -1396,
            1408,
            -646
          ],
          "rot": [
            0,
            0,
            0
          ],
          "params": 65535,
          "room": 0
        },
        {
          "id": 295,
          "pos": [
            -1060,
            1693,
            -51
          ],
          "rot": [
            0,
            2366,
            0
          ],
          "params": 7,
          "room": 0
        },
        {
          "id": 295,
          "pos": [
            -808,
            1753,
            -59
          ],
          "rot": [
            0,
            -16565,
            0
          ],
          "params": 8,
          "room": 0
        },
        {
          "id": 295,
          "pos": [
            -625,
            1793,
            -55
          ],
          "rot": [
            0,
            0,
            0
          ],
          "params": 10,
          "room": 0
        },
        {
          "id": 295,
          "pos": [
            -688,
            1943,
            -285
          ],
          "rot": [
            0,
            0,
            0
          ],
          "params": 32799,
          "room": 0
        }
      ],
      "objects": [
        1,
        258,
        0,
        512,
        0,
        28944,
        11,
        0,
        194,
        378,
        201,
        49,
        22,
        118
      ]
    }
  ],
  "actor_id_set": [
    21,
    27,
    38,
    57,
    59,
    76,
    146,
    149,
    155,
    180,
    205,
    208,
    229,
    294,
    295,
    321,
    333,
    334,
    337,
    387,
    389,
    430,
    441,
    463
  ],
  "total_actor_spawns": 52
}